logikal_utils/__init__.py
logikal_utils/docker.py
logikal_utils/download.py
logikal_utils/imports.py
logikal_utils/operators.py
logikal_utils/path.py
logikal_utils/project.py
logikal_utils/py.typed
logikal_utils/random.py
logikal_utils/string.py
logikal_utils/testing.py
logikal_utils-1.6.0.dist-info/licenses/LICENSE.txt
logikal_utils-1.6.0.dist-info/METADATA
logikal_utils-1.6.0.dist-info/WHEEL
logikal_utils-1.6.0.dist-info/top_level.txt
logikal_utils-1.6.0.dist-info/RECORD
