Metadata-Version: 2.4
Name: logikal-utils
Version: 1.6.0
Summary: Common Python utilities used at Logikal
Author-email: Logikal GmbH <contact@logikal.io>
License-Expression: MIT
Project-URL: Documentation, https://docs.logikal.io/logikal-utils/
Project-URL: Release notes, https://github.com/logikal-io/logikal-utils/releases
Project-URL: Issue tracker, https://github.com/logikal-io/logikal-utils/issues
Project-URL: Source code, https://github.com/logikal-io/logikal-utils
Keywords: python,utilities
Classifier: Development Status :: 5 - Production/Stable
Classifier: Intended Audience :: Developers
Classifier: Operating System :: POSIX :: Linux
Classifier: Programming Language :: Python :: 3
Classifier: Programming Language :: Python :: 3.12
Classifier: Topic :: Software Development
Classifier: Typing :: Typed
Requires-Python: ~=3.12
License-File: LICENSE.txt
Requires-Dist: termcolor~=3.3
Provides-Extra: docker
Requires-Dist: docker~=7.1; extra == "docker"
Provides-Extra: download
Requires-Dist: requests~=2.32; extra == "download"
Requires-Dist: tqdm~=4.67; extra == "download"
Dynamic: license-file
